ww_edit_objs/node/demo/README.md
ww_edit_objs/node/demo/批量导入 Wwise 后设置对象属性.flow.json
ww_edit_objs/node/icons/icon.png
ww_edit_objs/node/imp.js
ww_edit_objs/node/inmap/_default.inmap.json
ww_edit_objs/node/inmap/create_list.inmap.json
ww_edit_objs/node/inmap/ww_copy_objs.inmap.json
ww_edit_objs/node/inmap/ww_edit_objs.inmap.json
ww_edit_objs/node/inmap/ww_fill_soundbank.inmap.json
ww_edit_objs/node/inmap/ww_filter_objs.inmap.json
ww_edit_objs/node/inmap/ww_find_objs.inmap.json
ww_edit_objs/node/inmap/ww_get_selected_objs.inmap.json
ww_edit_objs/node/inmap/ww_get_targets_from_events.inmap.json
ww_edit_objs/node/inmap/ww_import_audio.inmap.json
ww_edit_objs/node/inmap/ww_import_by_template.inmap.json
ww_edit_objs/node/inmap/ww_import_music.inmap.json
ww_edit_objs/node/inmap/ww_select_objs.inmap.json
ww_edit_objs/node/inmap/ww_sync_tags.inmap.json
ww_edit_objs/node/node.html
ww_edit_objs/node/node.js
ww_edit_objs/node/node.nodered.json
ww_edit_objs/node/package.json
ww_edit_objs/node/plugin/select_wobj_properties/node.css
ww_edit_objs/node/plugin/select_wobj_properties/node.html
ww_edit_objs/node/plugin/select_wobj_properties/node.js
ww_edit_objs/node/test/default/flow.test.js
ww_edit_objs/run.bat
ww_edit_objs/run.sh
ww_edit_objs/src/ww_edit_objs.proto
ww_edit_objs/src/ww_edit_objs_cli.py
ww_edit_objs/src/ww_edit_objs_core.py
ww_edit_objs/src/ww_edit_objs_output.py
ww_edit_objs/src/ww_edit_objs_schema.json
ww_edit_objs-2.9.2.dist-info/METADATA
ww_edit_objs-2.9.2.dist-info/WHEEL
ww_edit_objs-2.9.2.dist-info/entry_points.txt
ww_edit_objs-2.9.2.dist-info/RECORD
