Metadata-Version: 2.1
Name: ww-edit-objs
Version: 2.9.2
Summary: 
Keywords: pubgrp.auditor,pubgrp.flow
Author: haoyu.zhou
Author-email: haoyu.zhou@mihoyo.com
Requires-Python: >=3.11,<3.12
Classifier: Programming Language :: Python :: 3
Classifier: Programming Language :: Python :: 3.11
Requires-Dist: miautil
Requires-Dist: miawwise
